{
  "_fv": 79,
  "_type": "projectile",
  "definition": {
    "projectileItem": {
      "value": "CUSTOM:PufferPower1"
    },
    "showParticles": false,
    "actionSound": {
      "value": "entity.arrow.shoot"
    },
    "igniteFire": false,
    "disableGravity": false,
    "power": 1.0,
    "damage": 2.0,
    "knockback": 2,
    "entityModel": "Modelmodel_Converted",
    "customModelTexture": "94.png",
    "modelWidth": 0.5,
    "modelHeight": 0.5,
    "onHitsPlayer": {
      "name": "Hetun2"
    },
    "onHitsEntity": {
      "name": "Hetun2"
    }
  }
}